Workbook

Sheet Dashboard
A1: CONSUMER STAPLES - COMPETITIVE & FINANCIAL ANALYSIS
A2: FY2025 Peer Comparison | Financial Quality, Competitive Position & Valuation
A4: FINANCIAL QUALITY RANKING | H4: VALUATION SNAPSHOT | N4: ROIC vs EV/EBITDA
A5: Rank | B5: Company | C5: ROIC | D5: EBIT Margin | E5: Revenue Growth | F5: FCF Margin | H5: Company | I5: EV / EBITDA | J5: P/E | K5: FCF Yield | N5: Company | O5: ROIC | P5: EV / EBITDA | Q5: LABEL
A6: 1 | B6: Colgate-Palmolive | C6: =Data!H2 -> 57.827869 | D6: =Data!D2 -> 20.768325 | E6: =Data!C2 -> 1.3979404 | F6: =Data!F2 -> 17.829457 | H6: Procter & Gamble | I6: =Valuation!F5 -> 15.31955 | J6: =Valuation!E5 -> 21.292859 | K6: =Valuation!H5 -> 4.1289836 | N6: Procter & Gamble | O6: =Valuation!D5 -> 26.246487 | P6: =Valuation!F5 -> 15.31955 | Q6: P&G
A7: 2 | B7: Procter & Gamble | C7: =Data!H3 -> 26.246487 | D7: =Data!D3 -> 24.264392 | E7: =Data!C3 -> 0.29153131 | F7: =Data!F3 -> 16.662712 | H7: Coca-Cola | I7: =Valuation!F6 -> 21.868277 | J7: =Valuation!E6 -> 28.910161 | K7: =Valuation!H6 -> 1.3976363 | N7: Coca-Cola | O7: =Valuation!D6 -> 24.106378 | P7: =Valuation!F6 -> 21.868277 | Q7: Coca-Cola
A8: 3 | B8: Coca-Cola | C8: =Data!H4 -> 24.106378 | D8: =Data!D4 -> 31.102814 | E8: =Data!C4 -> 1.8699135 | F8: =Data!F4 -> 11.046912 | H8: PepsiCo | I8: =Valuation!F7 -> 14.831116 | J8: =Valuation!E7 -> 22.815847 | K8: =Valuation!H7 -> 4.080795 | N8: PepsiCo | O8: =Valuation!D7 -> 22.197542 | P8: =Valuation!F7 -> 14.831116 | Q8: PepsiCo
A9: 4 | B9: PepsiCo | C9: =Data!H5 -> 22.197542 | D9: =Data!D5 -> 14.363588 | E9: =Data!C5 -> 2.254665 | F9: =Data!F5 -> 8.1682193 | H9: Colgate-Palmolive | I9: =Valuation!F8 -> 19.590251 | J9: =Valuation!E8 -> 33.191851 | K9: =Valuation!H8 -> 5.135305 | N9: Colgate-Palmolive | O9: =Valuation!D8 -> 57.827869 | P9: =Valuation!F8 -> 19.590251 | Q9: Colgate-Palmolive
A10: 5 | B10: Mondelez | C10: =Data!H6 -> 7.9530725 | D10: =Data!D6 -> 9.3935698 | E10: =Data!C6 -> 5.7517631 | F10: =Data!F6 -> 8.3945299 | H10: Mondelez | I10: =Valuation!F9 -> 19.836685 | J10: =Valuation!E9 -> 31.910307 | K10: =Valuation!H9 -> 4.1361854 | N10: Mondelez | O10: =Valuation!D9 -> 7.9530725 | P10: =Valuation!F9 -> 19.836685 | Q10: Mondelez
N12: Growth vs Valuation
A13: ANALYST TAKEAWAY | N13: Company | O13: Revenue Growth | P13: EV / EBITDA | Q13: LABEL
A14: FINANCIAL QUALITY | N14: Procter & Gamble | O14: =Valuation!C5 -> 0.29153131 | P14: =Valuation!F5 -> 15.31955 | Q14: P&G
A15: Colgate-Palmolive ranks #1 in the composite financial-quality assessment, supported by its leading ROIC, strong FCF margin and asset efficiency. P&G ranks #2, supported by strong margins and interest coverage. | N15: Coca-Cola | O15: =Valuation!C6 -> 1.8699135 | P15: =Valuation!F6 -> 21.868277 | Q15: Coca-Cola
A16: VALUATION | N16: PepsiCo | O16: =Valuation!C7 -> 2.254665 | P16: =Valuation!F7 -> 14.831116 | Q16: PepsiCo
A17: Coca-Cola trades at the highest EV/EBITDA multiple in the peer group at 21.9x, while PepsiCo has the lowest at 14.8x. Colgate-Palmolive trades at a 19.6x EV/EBITDA multiple, reflecting a premium relative to | N17: Colgate-Palmolive | O17: =Valuation!C8 -> 1.3979404 | P17: =Valuation!F8 -> 19.590251 | Q17: Colgate-Palmolive
A18: PepsiCo and P&G and supported by its superior ROIC and overall financial-quality ranking. | N18: Mondelez | O18: =Valuation!C9 -> 5.7517631 | P18: =Valuation!F9 -> 19.836685 | Q18: Mondelez
A19: Mondelez combines the strongest revenue growth with a 19.8x EV/EBITDA multiple, but its lower ROIC indicates that the market is placing a relatively high valuation on growth despite weaker current capital efficiency.
A20: CONCLUSION | N20: Competitive Positioning
A21: Colgate-Palmolive demonstrates the strongest overall financial profile, although its premium valuation suggests that investors already price in a significant portion of its superior capital efficiency.
N22: Company | O22: Key Strength | P22: Key Weakness
A23: KEY FINDING | N23: Colgate-Palmolive | O23: Capital efficiency | P23: Premium valuation
A24: Colgate-Palmolive ranks #1 in financial quality, while Mondelez leads growth and PepsiCo offers the lowest EV/EBITDA multiple. | N24: P&G | O24: Margin + financial stability | P24: Low growth
N25: Coca-Cola | O25: Strong margins/brand economics | P25: Premium valuation
N26: PepsiCo | O26: Diversification + reasonable valuation | P26: Higher leverage
N27: Mondelez | O27: Highest growth | P27: Lower ROIC

Sheet Financial Performance
A1: Financial Performance
A3: Company | B3: Revenue Growth | C3: EBIT Margin | D3: Net Margin | E3: FCF Margin
A4: Colgate-Palmolive | B4: =Data!C2 -> 1.3979404 | C4: =Data!D2 -> 20.768325 | D4: =Data!E2 -> 10.46021 | E4: =Data!F2 -> 17.829457
A5: Procter & Gamble | B5: =Data!C3 -> 0.29153131 | C5: =Data!D3 -> 24.264392 | D5: =Data!E3 -> 18.952589 | E5: =Data!F3 -> 16.662712
A6: Coca-Cola | B6: =Data!C4 -> 1.8699135 | C6: =Data!D4 -> 31.102814 | D6: =Data!E4 -> 27.339855 | E6: =Data!F4 -> 11.046912
A7: PepsiCo | B7: =Data!C5 -> 2.254665 | C7: =Data!D5 -> 14.363588 | D7: =Data!E5 -> 8.7729571 | E7: =Data!F5 -> 8.1682193
A8: Mondelez | B8: =Data!C6 -> 5.7517631 | C8: =Data!D6 -> 9.3935698 | D8: =Data!E6 -> 6.3601214 | E8: =Data!F6 -> 8.3945299

Sheet Profitability
A1: Profitability & Efficiency
A3: Company | B3: ROIC | C3: Asset Turnover
A4: Colgate-Palmolive | B4: =Data!H2 -> 57.827869 | C4: =Data!I2 -> 1.2481323
A5: Procter & Gamble | B5: =Data!H3 -> 26.246487 | C5: =Data!I3 -> 0.67302824
A6: Coca-Cola | B6: =Data!H4 -> 24.106378 | C6: =Data!I4 -> 0.45738246
A7: PepsiCo | B7: =Data!H5 -> 22.197542 | C7: =Data!I5 -> 0.87454259
A8: Mondelez | B8: =Data!H6 -> 7.9530725 | C8: =Data!I6 -> 0.53907704

Sheet Leverage
A1: Financial Health
A3: Company | B3: Debt / EBITDA | C3: Debt / Equity | D3: Interest Coverage
A4: Colgate-Palmolive | B4: =Data!K2 -> 2.1622851 | C4: =Data!L2 -> 158.40741 | D4: =Data!J2 -> 15.853933
A5: Procter & Gamble | B5: =Data!K3 -> 1.4825049 | C5: =Data!L3 -> 0.68182343 | D5: =Data!J3 -> 22.54796
A6: Coca-Cola | B6: =Data!K4 -> 2.4324671 | C6: =Data!L4 -> 1.4141565 | D6: =Data!J4 -> 9.0151149
A7: PepsiCo | B7: =Data!K5 -> 3.2105128 | C7: =Data!L5 -> 2.4454082 | D7: =Data!J5 -> 12.03479
A8: Mondelez | B8: =Data!K6 -> 4.3862402 | C8: =Data!L6 -> 0.84387336 | D8: =Data!J6 -> 6.0434057

Sheet Valuation
A1: Valuation Analysis
A2: Market data as of September 4, 2026 | D2: Financial data: FY2025
A4: Company | B4: Ticker | C4: Revenue Growth | D4: ROIC | E4: P E | F4: EV EBITDA | G4: P S | H4: FCF Yield
A5: Procter & Gamble | B5: PG | C5: 0.29153131 | D5: 26.246487 | E5: 21.292859 | F5: 15.31955 | G5: 4.0355481 | H5: 4.1289836
A6: Coca-Cola | B6: KO | C6: 1.8699135 | D6: 24.106378 | E6: 28.910161 | F6: 21.868277 | G6: 7.9039962 | H6: 1.3976363
A7: PepsiCo | B7: PEP | C7: 2.254665 | D7: 22.197542 | E7: 22.815847 | F7: 14.831116 | G7: 2.0016245 | H7: 4.080795
A8: Colgate-Palmolive | B8: CL | C8: 1.3979404 | D8: 57.827869 | E8: 33.191851 | F8: 19.590251 | G8: 3.4719374 | H8: 5.135305
A9: Mondelez | B9: MDLZ | C9: 5.7517631 | D9: 7.9530725 | E9: 31.910307 | F9: 19.836685 | G9: 2.0295343 | H9: 4.1361854

Sheet Rankings
A1: Overall Company Ranking
A3: Company | B3: Revenue Growth | C3: EBIT Margin | D3: ROIC | E3: FCF Margin | F3: Asset Turnover | G3: Interest Coverage | H3: Debt / EBITDA | I3: Growth Rank | J3: EBIT Rank | K3: ROIC Rank | L3: FCF Rank | M3: Asset Turnover Rank | N3: Interest Coverage Rank | O3: Debt/EBITDA Rank | P3: Average Rank | Q3: Overall Rank
A4: Colgate-Palmolive | B4: =Data!C2 -> 1.3979404 | C4: =Data!D2 -> 20.768325 | D4: =Data!H2 -> 57.827869 | E4: =Data!F2 -> 17.829457 | F4: =Data!I2 -> 1.2481323 | G4: =Data!J2 -> 15.853933 | H4: =Data!K2 -> 2.1622851 | I4: =RANK(B4,$B$4:$B$8,0) -> 4 | J4: =RANK(C4,$C$4:$C$8,0) -> 3 | K4: =RANK(D4,$D$4:$D$8,0) -> 1 | L4: =RANK(E4,$E$4:$E$8,0) -> 1 | M4: =RANK(F4,$F$4:$F$8,0) -> 1 | N4: =RANK(G4,$G$4:$G$8,0) -> 2 | O4: =RANK(H4,$H$4:$H$8,1) -> 2 | P4: =AVERAGE(I4:O4) -> 2 | Q4: =RANK(P4,$P$4:$P$8,1) -> 1
A5: Procter & Gamble | B5: =Data!C3 -> 0.29153131 | C5: =Data!D3 -> 24.264392 | D5: =Data!H3 -> 26.246487 | E5: =Data!F3 -> 16.662712 | F5: =Data!I3 -> 0.67302824 | G5: =Data!J3 -> 22.54796 | H5: =Data!K3 -> 1.4825049 | I5: =RANK(B5,$B$4:$B$8,0) -> 5 | J5: =RANK(C5,$C$4:$C$8,0) -> 2 | K5: =RANK(D5,$D$4:$D$8,0) -> 2 | L5: =RANK(E5,$E$4:$E$8,0) -> 2 | M5: =RANK(F5,$F$4:$F$8,0) -> 3 | N5: =RANK(G5,$G$4:$G$8,0) -> 1 | O5: =RANK(H5,$H$4:$H$8,1) -> 1 | P5: =AVERAGE(I5:O5) -> 2.2857143 | Q5: =RANK(P5,$P$4:$P$8,1) -> 2
A6: Coca-Cola | B6: =Data!C4 -> 1.8699135 | C6: =Data!D4 -> 31.102814 | D6: =Data!H4 -> 24.106378 | E6: =Data!F4 -> 11.046912 | F6: =Data!I4 -> 0.45738246 | G6: =Data!J4 -> 9.0151149 | H6: =Data!K4 -> 2.4324671 | I6: =RANK(B6,$B$4:$B$8,0) -> 3 | J6: =RANK(C6,$C$4:$C$8,0) -> 1 | K6: =RANK(D6,$D$4:$D$8,0) -> 3 | L6: =RANK(E6,$E$4:$E$8,0) -> 3 | M6: =RANK(F6,$F$4:$F$8,0) -> 5 | N6: =RANK(G6,$G$4:$G$8,0) -> 4 | O6: =RANK(H6,$H$4:$H$8,1) -> 3 | P6: =AVERAGE(I6:O6) -> 3.1428571 | Q6: =RANK(P6,$P$4:$P$8,1) -> 3
A7: PepsiCo | B7: =Data!C5 -> 2.254665 | C7: =Data!D5 -> 14.363588 | D7: =Data!H5 -> 22.197542 | E7: =Data!F5 -> 8.1682193 | F7: =Data!I5 -> 0.87454259 | G7: =Data!J5 -> 12.03479 | H7: =Data!K5 -> 3.2105128 | I7: =RANK(B7,$B$4:$B$8,0) -> 2 | J7: =RANK(C7,$C$4:$C$8,0) -> 4 | K7: =RANK(D7,$D$4:$D$8,0) -> 4 | L7: =RANK(E7,$E$4:$E$8,0) -> 5 | M7: =RANK(F7,$F$4:$F$8,0) -> 2 | N7: =RANK(G7,$G$4:$G$8,0) -> 3 | O7: =RANK(H7,$H$4:$H$8,1) -> 4 | P7: =AVERAGE(I7:O7) -> 3.4285714 | Q7: =RANK(P7,$P$4:$P$8,1) -> 4
A8: Mondelez | B8: =Data!C6 -> 5.7517631 | C8: =Data!D6 -> 9.3935698 | D8: =Data!H6 -> 7.9530725 | E8: =Data!F6 -> 8.3945299 | F8: =Data!I6 -> 0.53907704 | G8: =Data!J6 -> 6.0434057 | H8: =Data!K6 -> 4.3862402 | I8: =RANK(B8,$B$4:$B$8,0) -> 1 | J8: =RANK(C8,$C$4:$C$8,0) -> 5 | K8: =RANK(D8,$D$4:$D$8,0) -> 5 | L8: =RANK(E8,$E$4:$E$8,0) -> 4 | M8: =RANK(F8,$F$4:$F$8,0) -> 4 | N8: =RANK(G8,$G$4:$G$8,0) -> 5 | O8: =RANK(H8,$H$4:$H$8,1) -> 5 | P8: =AVERAGE(I8:O8) -> 4.1428571 | Q8: =RANK(P8,$P$4:$P$8,1) -> 5

Sheet Data
A1: Company | B1: Ticker | C1: Revenue Growth | D1: EBIT Margin | E1: Net Margin | F1: FCF Margin | G1: ROE | H1: ROIC | I1: Asset Turnover | J1: Interest Coverage | K1: Debt to EBITDA | L1: Debt to Equity | M1: Overall Rank
A2: Colgate-Palmolive | B2: CL | C2: 1.3979404 | D2: 20.768325 | E2: 10.46021 | F2: 17.829457 | G2: 3948.1481 | H2: 57.827869 | I2: 1.2481323 | J2: 15.853933 | K2: 2.1622851 | L2: 158.40741 | M2: 1
A3: Procter & Gamble | B3: PG | C3: 0.29153131 | D3: 24.264392 | E3: 18.952589 | F3: 16.662712 | G3: 30.712143 | H3: 26.246487 | I3: 0.67302824 | J3: 22.54796 | K3: 1.4825049 | L3: 0.68182343 | M3: 2
A4: Coca-Cola | B4: KO | C4: 1.8699135 | D4: 31.102814 | E4: 27.339855 | F4: 11.046912 | G4: 40.744195 | H4: 24.106378 | I4: 0.45738246 | J4: 9.0151149 | K4: 2.4324671 | L4: 1.4141565 | M4: 3
A5: PepsiCo | B5: PEP | C5: 2.254665 | D5: 14.363588 | E5: 8.7729571 | F5: 8.1682193 | G5: 40.38028 | H5: 22.197542 | I5: 0.87454259 | J5: 12.03479 | K5: 3.2105128 | L5: 2.4454082 | M5: 4
A6: Mondelez | B6: MDLZ | C6: 5.7517631 | D6: 9.3935698 | E6: 6.3601214 | F6: 8.3945299 | G6: 9.4860283 | H6: 7.9530725 | I6: 0.53907703 | J6: 6.0434057 | K6: 4.3862402 | L6: 0.84387336 | M6: 5

Sheet Methodology
A1: Methodology
A3: Objective
A4: Compare the financial quality, operating efficiency, leverage and relative valuation of five major consumer-staples companies using FY2025 financial data.
A6: Companies
A7: Colgate-Palmolive
A8: Procter & Gamble
A9: Coca-Cola
A10: PepsiCo
A11: Mondelez
A13: Financial quality score
A14: Companies are ranked across seven metrics. Higher values receive better ranks for growth, profitability, cash generation, efficiency and interest coverage. Lower Debt/EBITDA receives a better rank. The average of the seven metric ranks determines the overall financial-quality ranking.
A15: ROIC is calculated as EBIT divided by year-end invested capital (equity + debt − cash) and is used as a simplified capital-efficiency measure.
... A27: Market valuation date: 2026-09-04
